{
  "updated_at": "2026-06-11T02:12:33.702872Z",
  "bbox": {
    "lat_min": 15,
    "lat_max": 35,
    "lon_min": 110,
    "lon_max": 128
  },
  "data_range": {
    "start": "2026-05-12",
    "end": "2026-06-11"
  },
  "overall": {
    "total_detections": 11122,
    "dark_vessels": 3210,
    "dark_ratio": 28.9,
    "dark_by_date": {
      "2026-05-13": 15,
      "2026-05-14": 165,
      "2026-05-16": 205,
      "2026-05-17": 306,
      "2026-05-18": 315,
      "2026-05-20": 58,
      "2026-05-21": 169,
      "2026-05-22": 59,
      "2026-05-23": 464,
      "2026-05-24": 173,
      "2026-05-25": 20,
      "2026-05-26": 98,
      "2026-05-28": 226,
      "2026-05-29": 272,
      "2026-06-01": 33,
      "2026-06-02": 152,
      "2026-06-03": 44,
      "2026-06-04": 196,
      "2026-06-05": 123,
      "2026-06-06": 12,
      "2026-06-07": 105
    }
  },
  "regions": {
    "taiwan_region": {
      "name": "台灣周邊海域",
      "total_detections": 11122,
      "dark_vessels": 3210,
      "matched_vessels": 7912,
      "dark_ratio": 28.9,
      "dark_by_date": {
        "2026-05-13": 15,
        "2026-05-14": 165,
        "2026-05-16": 205,
        "2026-05-17": 306,
        "2026-05-18": 315,
        "2026-05-20": 58,
        "2026-05-21": 169,
        "2026-05-22": 59,
        "2026-05-23": 464,
        "2026-05-24": 173,
        "2026-05-25": 20,
        "2026-05-26": 98,
        "2026-05-28": 226,
        "2026-05-29": 272,
        "2026-06-01": 33,
        "2026-06-02": 152,
        "2026-06-03": 44,
        "2026-06-04": 196,
        "2026-06-05": 123,
        "2026-06-06": 12,
        "2026-06-07": 105
      },
      "matched_by_flag": {
        "CHN": 5196,
        "PAN": 583,
        "UNKNOWN": 149,
        "NLD": 20,
        "HKG": 256,
        "CMR": 13,
        "KOR": 250,
        "MHL": 212,
        "IRL": 1,
        "LBR": 315,
        "PRT": 20,
        "TWN": 175,
        "SGP": 215,
        "BHS": 39,
        "BLZ": 26,
        "COM": 7,
        "CYP": 30,
        "VNM": 22,
        "ATG": 8,
        "DNK": 16,
        "PLW": 7,
        "MLT": 56,
        "SLE": 27,
        "MAR": 1,
        "BRN": 2,
        "JPN": 16,
        "BEL": 14,
        "RUS": 12,
        "GRC": 7,
        "GBR": 20,
        "STP": 9,
        "BRB": 3,
        "VUT": 4,
        "DEU": 4,
        "PHL": 11,
        "IDN": 11,
        "THA": 14,
        "SMR": 2,
        "GNB": 8,
        "BMU": 6,
        "IND": 4,
        "KNA": 10,
        "FRO": 2,
        "LUX": 3,
        "NOR": 10,
        "JAM": 4,
        "MYS": 9,
        "MNG": 5,
        "MOZ": 3,
        "IRN": 7,
        "ZAF": 1,
        "PRK": 7,
        "FRA": 6,
        "USA": 1,
        "VAT": 1,
        "GMB": 3,
        "OMN": 5,
        "CYM": 1,
        "ITA": 3,
        "SAU": 4,
        "CAF": 1,
        "TGO": 3,
        "BGD": 5,
        "GIB": 1,
        "TUV": 3,
        "HUN": 1,
        "TZA": 8,
        "MAC": 1,
        "AND": 1,
        "DJI": 1,
        "AGO": 2,
        "MCO": 1,
        "ALB": 1,
        "ETH": 1,
        "ABW": 1,
        "TUR": 1,
        "GTM": 1,
        "SEN": 1,
        "BES": 1,
        "SOM": 1
      },
      "dark_details": [
        {
          "lat": 21.66,
          "lon": 112.41,
          "date": "2026-05-29",
          "detections": 1
        },
        {
          "lat": 19.73,
          "lon": 120.3,
          "date": "2026-05-18",
          "detections": 1
        },
        {
          "lat": 24.38,
          "lon": 122.15,
          "date": "2026-05-18",
          "detections": 1
        },
        {
          "lat": 25.88,
          "lon": 119.68,
          "date": "2026-06-02",
          "detections": 1
        },
        {
          "lat": 27.53,
          "lon": 120.9,
          "date": "2026-05-16",
          "detections": 1
        },
        {
          "lat": 31.18,
          "lon": 122.11,
          "date": "2026-05-23",
          "detections": 1
        },
        {
          "lat": 19.63,
          "lon": 112.65,
          "date": "2026-05-29",
          "detections": 1
        },
        {
          "lat": 30.0,
          "lon": 123.1,
          "date": "2026-06-04",
          "detections": 1
        },
        {
          "lat": 31.13,
          "lon": 122.95,
          "date": "2026-05-23",
          "detections": 1
        },
        {
          "lat": 23.18,
          "lon": 116.77,
          "date": "2026-05-14",
          "detections": 1
        },
        {
          "lat": 21.22,
          "lon": 111.22,
          "date": "2026-05-17",
          "detections": 1
        },
        {
          "lat": 21.64,
          "lon": 112.22,
          "date": "2026-05-29",
          "detections": 1
        },
        {
          "lat": 31.29,
          "lon": 122.86,
          "date": "2026-05-23",
          "detections": 1
        },
        {
          "lat": 29.06,
          "lon": 121.8,
          "date": "2026-05-23",
          "detections": 1
        },
        {
          "lat": 24.49,
          "lon": 120.07,
          "date": "2026-05-18",
          "detections": 1
        },
        {
          "lat": 32.46,
          "lon": 121.36,
          "date": "2026-05-23",
          "detections": 1
        },
        {
          "lat": 22.79,
          "lon": 119.77,
          "date": "2026-05-18",
          "detections": 1
        },
        {
          "lat": 24.73,
          "lon": 119.74,
          "date": "2026-05-18",
          "detections": 1
        },
        {
          "lat": 33.95,
          "lon": 126.43,
          "date": "2026-05-20",
          "detections": 1
        },
        {
          "lat": 21.5,
          "lon": 111.82,
          "date": "2026-05-17",
          "detections": 1
        },
        {
          "lat": 29.1,
          "lon": 122.26,
          "date": "2026-06-04",
          "detections": 1
        },
        {
          "lat": 24.79,
          "lon": 121.87,
          "date": "2026-05-28",
          "detections": 1
        },
        {
          "lat": 20.9,
          "lon": 110.99,
          "date": "2026-05-17",
          "detections": 1
        },
        {
          "lat": 22.01,
          "lon": 120.65,
          "date": "2026-05-18",
          "detections": 1
        },
        {
          "lat": 29.54,
          "lon": 122.83,
          "date": "2026-05-23",
          "detections": 1
        },
        {
          "lat": 21.35,
          "lon": 112.72,
          "date": "2026-06-05",
          "detections": 1
        },
        {
          "lat": 30.79,
          "lon": 122.0,
          "date": "2026-06-04",
          "detections": 1
        },
        {
          "lat": 31.69,
          "lon": 122.81,
          "date": "2026-05-23",
          "detections": 1
        },
        {
          "lat": 20.68,
          "lon": 111.94,
          "date": "2026-05-29",
          "detections": 1
        },
        {
          "lat": 18.74,
          "lon": 110.74,
          "date": "2026-05-22",
          "detections": 1
        },
        {
          "lat": 19.91,
          "lon": 111.14,
          "date": "2026-05-17",
          "detections": 1
        },
        {
          "lat": 21.38,
          "lon": 113.39,
          "date": "2026-05-24",
          "detections": 1
        },
        {
          "lat": 21.01,
          "lon": 110.75,
          "date": "2026-05-17",
          "detections": 1
        },
        {
          "lat": 23.26,
          "lon": 117.05,
          "date": "2026-06-07",
          "detections": 1
        },
        {
          "lat": 30.96,
          "lon": 122.48,
          "date": "2026-05-23",
          "detections": 1
        },
        {
          "lat": 30.38,
          "lon": 122.46,
          "date": "2026-06-04",
          "detections": 1
        },
        {
          "lat": 27.48,
          "lon": 120.87,
          "date": "2026-05-16",
          "detections": 1
        },
        {
          "lat": 24.67,
          "lon": 119.5,
          "date": "2026-05-21",
          "detections": 1
        },
        {
          "lat": 34.9,
          "lon": 119.96,
          "date": "2026-05-28",
          "detections": 1
        },
        {
          "lat": 15.07,
          "lon": 119.95,
          "date": "2026-05-25",
          "detections": 1
        },
        {
          "lat": 25.41,
          "lon": 121.47,
          "date": "2026-05-18",
          "detections": 1
        },
        {
          "lat": 23.65,
          "lon": 117.58,
          "date": "2026-05-26",
          "detections": 1
        },
        {
          "lat": 20.23,
          "lon": 110.43,
          "date": "2026-05-22",
          "detections": 1
        },
        {
          "lat": 20.88,
          "lon": 113.08,
          "date": "2026-05-24",
          "detections": 1
        },
        {
          "lat": 23.85,
          "lon": 122.37,
          "date": "2026-05-28",
          "detections": 1
        },
        {
          "lat": 18.37,
          "lon": 110.11,
          "date": "2026-06-03",
          "detections": 1
        },
        {
          "lat": 21.18,
          "lon": 113.01,
          "date": "2026-06-05",
          "detections": 1
        },
        {
          "lat": 16.07,
          "lon": 120.19,
          "date": "2026-05-18",
          "detections": 1
        },
        {
          "lat": 19.56,
          "lon": 111.25,
          "date": "2026-05-29",
          "detections": 1
        },
        {
          "lat": 32.26,
          "lon": 121.55,
          "date": "2026-05-23",
          "detections": 1
        },
        {
          "lat": 23.9,
          "lon": 118.19,
          "date": "2026-05-14",
          "detections": 1
        },
        {
          "lat": 30.67,
          "lon": 122.0,
          "date": "2026-05-23",
          "detections": 1
        },
        {
          "lat": 31.63,
          "lon": 121.26,
          "date": "2026-05-23",
          "detections": 1
        },
        {
          "lat": 28.27,
          "lon": 122.16,
          "date": "2026-05-23",
          "detections": 1
        },
        {
          "lat": 20.54,
          "lon": 112.0,
          "date": "2026-05-17",
          "detections": 1
        },
        {
          "lat": 24.91,
          "lon": 120.11,
          "date": "2026-06-02",
          "detections": 1
        },
        {
          "lat": 23.55,
          "lon": 117.45,
          "date": "2026-05-26",
          "detections": 1
        },
        {
          "lat": 23.36,
          "lon": 116.58,
          "date": "2026-06-07",
          "detections": 1
        },
        {
          "lat": 22.76,
          "lon": 120.16,
          "date": "2026-05-18",
          "detections": 1
        },
        {
          "lat": 25.06,
          "lon": 119.87,
          "date": "2026-05-18",
          "detections": 1
        },
        {
          "lat": 32.66,
          "lon": 121.99,
          "date": "2026-05-23",
          "detections": 1
        },
        {
          "lat": 24.34,
          "lon": 120.13,
          "date": "2026-05-18",
          "detections": 1
        },
        {
          "lat": 20.67,
          "lon": 112.26,
          "date": "2026-05-17",
          "detections": 1
        },
        {
          "lat": 21.0,
          "lon": 112.23,
          "date": "2026-05-29",
          "detections": 1
        },
        {
          "lat": 30.75,
          "lon": 121.96,
          "date": "2026-06-04",
          "detections": 1
        },
        {
          "lat": 29.28,
          "lon": 122.09,
          "date": "2026-05-23",
          "detections": 1
        },
        {
          "lat": 24.03,
          "lon": 119.54,
          "date": "2026-06-02",
          "detections": 1
        },
        {
          "lat": 21.33,
          "lon": 113.72,
          "date": "2026-06-05",
          "detections": 1
        },
        {
          "lat": 21.21,
          "lon": 111.01,
          "date": "2026-05-17",
          "detections": 1
        },
        {
          "lat": 24.0,
          "lon": 118.97,
          "date": "2026-06-02",
          "detections": 1
        },
        {
          "lat": 23.96,
          "lon": 120.18,
          "date": "2026-05-16",
          "detections": 1
        },
        {
          "lat": 24.85,
          "lon": 118.69,
          "date": "2026-05-21",
          "detections": 1
        },
        {
          "lat": 20.67,
          "lon": 112.26,
          "date": "2026-05-29",
          "detections": 1
        },
        {
          "lat": 28.1,
          "lon": 121.89,
          "date": "2026-05-23",
          "detections": 1
        },
        {
          "lat": 19.82,
          "lon": 112.36,
          "date": "2026-05-29",
          "detections": 1
        },
        {
          "lat": 21.4,
          "lon": 112.15,
          "date": "2026-05-29",
          "detections": 1
        },
        {
          "lat": 21.44,
          "lon": 111.07,
          "date": "2026-05-17",
          "detections": 1
        },
        {
          "lat": 21.94,
          "lon": 114.1,
          "date": "2026-05-24",
          "detections": 1
        },
        {
          "lat": 20.8,
          "lon": 112.71,
          "date": "2026-06-05",
          "detections": 1
        },
        {
          "lat": 24.31,
          "lon": 118.22,
          "date": "2026-05-14",
          "detections": 1
        },
        {
          "lat": 25.26,
          "lon": 119.54,
          "date": "2026-06-02",
          "detections": 1
        },
        {
          "lat": 26.5,
          "lon": 120.73,
          "date": "2026-05-28",
          "detections": 1
        },
        {
          "lat": 22.3,
          "lon": 113.88,
          "date": "2026-06-05",
          "detections": 2
        },
        {
          "lat": 29.67,
          "lon": 122.55,
          "date": "2026-05-23",
          "detections": 1
        },
        {
          "lat": 20.93,
          "lon": 110.89,
          "date": "2026-05-17",
          "detections": 1
        },
        {
          "lat": 29.03,
          "lon": 122.94,
          "date": "2026-05-23",
          "detections": 1
        },
        {
          "lat": 26.91,
          "lon": 120.52,
          "date": "2026-05-28",
          "detections": 1
        },
        {
          "lat": 29.14,
          "lon": 122.42,
          "date": "2026-05-23",
          "detections": 1
        },
        {
          "lat": 21.63,
          "lon": 111.8,
          "date": "2026-05-29",
          "detections": 1
        },
        {
          "lat": 21.03,
          "lon": 110.83,
          "date": "2026-05-17",
          "detections": 1
        },
        {
          "lat": 34.88,
          "lon": 127.95,
          "date": "2026-06-01",
          "detections": 1
        },
        {
          "lat": 22.97,
          "lon": 116.93,
          "date": "2026-05-26",
          "detections": 1
        },
        {
          "lat": 18.62,
          "lon": 110.22,
          "date": "2026-05-22",
          "detections": 1
        },
        {
          "lat": 31.45,
          "lon": 122.73,
          "date": "2026-05-23",
          "detections": 1
        },
        {
          "lat": 26.45,
          "lon": 119.96,
          "date": "2026-05-28",
          "detections": 1
        },
        {
          "lat": 25.47,
          "lon": 121.55,
          "date": "2026-05-16",
          "detections": 1
        },
        {
          "lat": 21.39,
          "lon": 112.32,
          "date": "2026-05-29",
          "detections": 1
        },
        {
          "lat": 34.81,
          "lon": 119.39,
          "date": "2026-05-28",
          "detections": 1
        },
        {
          "lat": 26.63,
          "lon": 120.14,
          "date": "2026-05-16",
          "detections": 1
        },
        {
          "lat": 32.44,
          "lon": 122.14,
          "date": "2026-05-23",
          "detections": 1
        },
        {
          "lat": 25.02,
          "lon": 119.86,
          "date": "2026-05-18",
          "detections": 1
        },
        {
          "lat": 31.08,
          "lon": 122.85,
          "date": "2026-05-23",
          "detections": 1
        },
        {
          "lat": 24.05,
          "lon": 121.69,
          "date": "2026-05-18",
          "detections": 1
        },
        {
          "lat": 25.15,
          "lon": 119.85,
          "date": "2026-05-21",
          "detections": 1
        },
        {
          "lat": 23.89,
          "lon": 117.52,
          "date": "2026-06-07",
          "detections": 1
        },
        {
          "lat": 22.56,
          "lon": 121.72,
          "date": "2026-05-18",
          "detections": 1
        },
        {
          "lat": 22.65,
          "lon": 122.45,
          "date": "2026-05-16",
          "detections": 1
        },
        {
          "lat": 25.18,
          "lon": 121.31,
          "date": "2026-05-18",
          "detections": 1
        },
        {
          "lat": 24.38,
          "lon": 120.12,
          "date": "2026-05-18",
          "detections": 1
        },
        {
          "lat": 25.62,
          "lon": 121.0,
          "date": "2026-05-18",
          "detections": 1
        },
        {
          "lat": 30.98,
          "lon": 122.48,
          "date": "2026-06-04",
          "detections": 1
        },
        {
          "lat": 30.83,
          "lon": 121.77,
          "date": "2026-06-04",
          "detections": 1
        },
        {
          "lat": 23.33,
          "lon": 117.53,
          "date": "2026-06-07",
          "detections": 1
        },
        {
          "lat": 25.62,
          "lon": 120.07,
          "date": "2026-05-18",
          "detections": 1
        },
        {
          "lat": 22.34,
          "lon": 114.0,
          "date": "2026-05-24",
          "detections": 1
        },
        {
          "lat": 34.88,
          "lon": 127.95,
          "date": "2026-05-20",
          "detections": 1
        },
        {
          "lat": 25.17,
          "lon": 121.35,
          "date": "2026-05-18",
          "detections": 1
        },
        {
          "lat": 21.05,
          "lon": 110.64,
          "date": "2026-05-29",
          "detections": 1
        },
        {
          "lat": 30.2,
          "lon": 121.86,
          "date": "2026-05-23",
          "detections": 1
        },
        {
          "lat": 23.92,
          "lon": 117.87,
          "date": "2026-05-14",
          "detections": 1
        },
        {
          "lat": 18.82,
          "lon": 121.03,
          "date": "2026-05-25",
          "detections": 1
        },
        {
          "lat": 21.7,
          "lon": 111.95,
          "date": "2026-05-29",
          "detections": 1
        },
        {
          "lat": 20.84,
          "lon": 111.2,
          "date": "2026-05-17",
          "detections": 1
        },
        {
          "lat": 25.09,
          "lon": 119.9,
          "date": "2026-05-21",
          "detections": 1
        },
        {
          "lat": 25.29,
          "lon": 120.98,
          "date": "2026-05-18",
          "detections": 1
        },
        {
          "lat": 20.35,
          "lon": 118.93,
          "date": "2026-05-18",
          "detections": 1
        },
        {
          "lat": 24.86,
          "lon": 119.0,
          "date": "2026-05-21",
          "detections": 1
        },
        {
          "lat": 23.17,
          "lon": 122.03,
          "date": "2026-05-28",
          "detections": 1
        },
        {
          "lat": 25.55,
          "lon": 119.66,
          "date": "2026-05-21",
          "detections": 2
        },
        {
          "lat": 34.66,
          "lon": 119.85,
          "date": "2026-05-28",
          "detections": 1
        },
        {
          "lat": 23.97,
          "lon": 120.11,
          "date": "2026-05-16",
          "detections": 1
        },
        {
          "lat": 26.41,
          "lon": 119.93,
          "date": "2026-05-28",
          "detections": 1
        },
        {
          "lat": 19.35,
          "lon": 111.83,
          "date": "2026-05-29",
          "detections": 1
        },
        {
          "lat": 20.35,
          "lon": 112.01,
          "date": "2026-05-17",
          "detections": 1
        },
        {
          "lat": 21.27,
          "lon": 111.29,
          "date": "2026-05-17",
          "detections": 1
        },
        {
          "lat": 25.85,
          "lon": 121.63,
          "date": "2026-05-16",
          "detections": 1
        },
        {
          "lat": 18.01,
          "lon": 122.56,
          "date": "2026-05-13",
          "detections": 1
        },
        {
          "lat": 19.19,
          "lon": 110.77,
          "date": "2026-06-03",
          "detections": 1
        },
        {
          "lat": 29.67,
          "lon": 122.81,
          "date": "2026-06-04",
          "detections": 1
        },
        {
          "lat": 25.32,
          "lon": 119.37,
          "date": "2026-05-21",
          "detections": 1
        },
        {
          "lat": 30.28,
          "lon": 121.82,
          "date": "2026-06-04",
          "detections": 1
        },
        {
          "lat": 23.11,
          "lon": 117.67,
          "date": "2026-05-14",
          "detections": 1
        },
        {
          "lat": 28.81,
          "lon": 121.89,
          "date": "2026-06-04",
          "detections": 1
        },
        {
          "lat": 34.86,
          "lon": 119.82,
          "date": "2026-05-16",
          "detections": 1
        },
        {
          "lat": 25.84,
          "lon": 120.06,
          "date": "2026-05-18",
          "detections": 1
        },
        {
          "lat": 34.82,
          "lon": 119.6,
          "date": "2026-05-28",
          "detections": 1
        },
        {
          "lat": 25.49,
          "lon": 120.75,
          "date": "2026-05-18",
          "detections": 1
        },
        {
          "lat": 19.31,
          "lon": 121.06,
          "date": "2026-05-25",
          "detections": 1
        },
        {
          "lat": 27.48,
          "lon": 120.7,
          "date": "2026-05-28",
          "detections": 1
        },
        {
          "lat": 23.5,
          "lon": 117.06,
          "date": "2026-05-14",
          "detections": 1
        },
        {
          "lat": 25.56,
          "lon": 119.7,
          "date": "2026-05-21",
          "detections": 2
        },
        {
          "lat": 29.16,
          "lon": 123.1,
          "date": "2026-05-23",
          "detections": 1
        },
        {
          "lat": 26.5,
          "lon": 120.0,
          "date": "2026-05-28",
          "detections": 1
        },
        {
          "lat": 21.56,
          "lon": 114.29,
          "date": "2026-05-24",
          "detections": 1
        },
        {
          "lat": 27.04,
          "lon": 121.31,
          "date": "2026-05-28",
          "detections": 1
        },
        {
          "lat": 18.68,
          "lon": 111.06,
          "date": "2026-05-22",
          "detections": 1
        },
        {
          "lat": 21.58,
          "lon": 112.33,
          "date": "2026-05-24",
          "detections": 1
        },
        {
          "lat": 24.47,
          "lon": 118.2,
          "date": "2026-05-14",
          "detections": 1
        },
        {
          "lat": 21.04,
          "lon": 111.74,
          "date": "2026-05-29",
          "detections": 1
        },
        {
          "lat": 31.92,
          "lon": 122.04,
          "date": "2026-05-23",
          "detections": 1
        },
        {
          "lat": 23.25,
          "lon": 116.97,
          "date": "2026-05-26",
          "detections": 1
        },
        {
          "lat": 24.42,
          "lon": 119.45,
          "date": "2026-06-02",
          "detections": 1
        },
        {
          "lat": 20.24,
          "lon": 110.93,
          "date": "2026-05-17",
          "detections": 1
        },
        {
          "lat": 22.55,
          "lon": 116.25,
          "date": "2026-05-26",
          "detections": 1
        },
        {
          "lat": 21.23,
          "lon": 112.12,
          "date": "2026-05-17",
          "detections": 1
        },
        {
          "lat": 26.49,
          "lon": 120.08,
          "date": "2026-05-28",
          "detections": 1
        },
        {
          "lat": 31.7,
          "lon": 121.67,
          "date": "2026-05-23",
          "detections": 1
        },
        {
          "lat": 20.74,
          "lon": 112.41,
          "date": "2026-06-05",
          "detections": 1
        },
        {
          "lat": 20.92,
          "lon": 110.44,
          "date": "2026-05-29",
          "detections": 1
        },
        {
          "lat": 24.96,
          "lon": 119.11,
          "date": "2026-06-02",
          "detections": 1
        },
        {
          "lat": 21.18,
          "lon": 112.12,
          "date": "2026-05-29",
          "detections": 1
        },
        {
          "lat": 27.18,
          "lon": 120.69,
          "date": "2026-05-16",
          "detections": 1
        },
        {
          "lat": 23.5,
          "lon": 117.08,
          "date": "2026-05-14",
          "detections": 1
        },
        {
          "lat": 21.06,
          "lon": 110.76,
          "date": "2026-05-17",
          "detections": 1
        },
        {
          "lat": 21.3,
          "lon": 112.62,
          "date": "2026-06-05",
          "detections": 1
        },
        {
          "lat": 26.26,
          "lon": 119.91,
          "date": "2026-05-21",
          "detections": 1
        },
        {
          "lat": 25.19,
          "lon": 120.27,
          "date": "2026-05-18",
          "detections": 1
        },
        {
          "lat": 30.41,
          "lon": 122.83,
          "date": "2026-05-23",
          "detections": 1
        },
        {
          "lat": 29.94,
          "lon": 122.17,
          "date": "2026-06-04",
          "detections": 1
        },
        {
          "lat": 23.27,
          "lon": 122.28,
          "date": "2026-05-28",
          "detections": 1
        },
        {
          "lat": 28.03,
          "lon": 122.47,
          "date": "2026-06-04",
          "detections": 1
        },
        {
          "lat": 21.17,
          "lon": 111.04,
          "date": "2026-05-29",
          "detections": 1
        },
        {
          "lat": 25.45,
          "lon": 119.23,
          "date": "2026-05-21",
          "detections": 1
        },
        {
          "lat": 29.53,
          "lon": 122.51,
          "date": "2026-05-23",
          "detections": 2
        },
        {
          "lat": 22.86,
          "lon": 117.78,
          "date": "2026-05-26",
          "detections": 1
        },
        {
          "lat": 32.35,
          "lon": 121.57,
          "date": "2026-05-23",
          "detections": 1
        },
        {
          "lat": 23.46,
          "lon": 116.96,
          "date": "2026-05-14",
          "detections": 1
        },
        {
          "lat": 30.07,
          "lon": 121.96,
          "date": "2026-06-04",
          "detections": 1
        },
        {
          "lat": 25.32,
          "lon": 119.54,
          "date": "2026-06-02",
          "detections": 1
        },
        {
          "lat": 28.74,
          "lon": 122.07,
          "date": "2026-06-04",
          "detections": 1
        },
        {
          "lat": 21.74,
          "lon": 114.45,
          "date": "2026-06-05",
          "detections": 1
        },
        {
          "lat": 22.16,
          "lon": 114.32,
          "date": "2026-05-24",
          "detections": 1
        },
        {
          "lat": 22.99,
          "lon": 117.13,
          "date": "2026-05-26",
          "detections": 1
        },
        {
          "lat": 23.92,
          "lon": 118.0,
          "date": "2026-05-14",
          "detections": 1
        },
        {
          "lat": 30.56,
          "lon": 121.88,
          "date": "2026-05-23",
          "detections": 1
        },
        {
          "lat": 24.09,
          "lon": 118.08,
          "date": "2026-05-21",
          "detections": 1
        },
        {
          "lat": 21.39,
          "lon": 112.06,
          "date": "2026-05-17",
          "detections": 1
        },
        {
          "lat": 24.24,
          "lon": 118.13,
          "date": "2026-06-07",
          "detections": 1
        },
        {
          "lat": 22.76,
          "lon": 116.63,
          "date": "2026-06-07",
          "detections": 1
        },
        {
          "lat": 24.87,
          "lon": 119.96,
          "date": "2026-06-02",
          "detections": 1
        },
        {
          "lat": 30.47,
          "lon": 122.73,
          "date": "2026-05-23",
          "detections": 1
        },
        {
          "lat": 28.13,
          "lon": 122.48,
          "date": "2026-05-23",
          "detections": 1
        },
        {
          "lat": 26.27,
          "lon": 119.87,
          "date": "2026-05-21",
          "detections": 1
        },
        {
          "lat": 19.27,
          "lon": 110.86,
          "date": "2026-05-29",
          "detections": 1
        },
        {
          "lat": 22.74,
          "lon": 116.22,
          "date": "2026-06-07",
          "detections": 1
        },
        {
          "lat": 32.0,
          "lon": 121.92,
          "date": "2026-05-23",
          "detections": 1
        },
        {
          "lat": 23.59,
          "lon": 118.09,
          "date": "2026-05-26",
          "detections": 1
        },
        {
          "lat": 24.15,
          "lon": 119.69,
          "date": "2026-06-02",
          "detections": 1
        },
        {
          "lat": 21.79,
          "lon": 113.13,
          "date": "2026-05-24",
          "detections": 1
        },
        {
          "lat": 26.44,
          "lon": 119.96,
          "date": "2026-05-16",
          "detections": 1
        },
        {
          "lat": 23.83,
          "lon": 117.52,
          "date": "2026-06-07",
          "detections": 1
        },
        {
          "lat": 34.27,
          "lon": 126.67,
          "date": "2026-06-01",
          "detections": 1
        },
        {
          "lat": 30.05,
          "lon": 121.72,
          "date": "2026-05-23",
          "detections": 1
        },
        {
          "lat": 29.05,
          "lon": 122.6,
          "date": "2026-05-23",
          "detections": 1
        },
        {
          "lat": 21.29,
          "lon": 112.19,
          "date": "2026-05-29",
          "detections": 1
        },
        {
          "lat": 23.95,
          "lon": 117.85,
          "date": "2026-05-14",
          "detections": 1
        },
        {
          "lat": 22.84,
          "lon": 117.43,
          "date": "2026-05-14",
          "detections": 1
        },
        {
          "lat": 21.15,
          "lon": 110.94,
          "date": "2026-05-17",
          "detections": 1
        },
        {
          "lat": 31.86,
          "lon": 122.65,
          "date": "2026-05-23",
          "detections": 1
        },
        {
          "lat": 23.42,
          "lon": 118.13,
          "date": "2026-05-14",
          "detections": 1
        },
        {
          "lat": 20.58,
          "lon": 110.59,
          "date": "2026-06-03",
          "detections": 1
        },
        {
          "lat": 23.79,
          "lon": 117.47,
          "date": "2026-06-07",
          "detections": 1
        },
        {
          "lat": 23.99,
          "lon": 120.13,
          "date": "2026-05-28",
          "detections": 1
        },
        {
          "lat": 24.93,
          "lon": 122.02,
          "date": "2026-05-18",
          "detections": 1
        },
        {
          "lat": 24.47,
          "lon": 119.5,
          "date": "2026-05-21",
          "detections": 2
        },
        {
          "lat": 22.7,
          "lon": 116.7,
          "date": "2026-05-14",
          "detections": 1
        },
        {
          "lat": 24.99,
          "lon": 119.87,
          "date": "2026-06-02",
          "detections": 1
        },
        {
          "lat": 20.45,
          "lon": 112.0,
          "date": "2026-05-17",
          "detections": 1
        },
        {
          "lat": 22.1,
          "lon": 114.0,
          "date": "2026-05-24",
          "detections": 1
        },
        {
          "lat": 21.08,
          "lon": 112.15,
          "date": "2026-05-29",
          "detections": 1
        },
        {
          "lat": 30.49,
          "lon": 121.95,
          "date": "2026-05-23",
          "detections": 1
        },
        {
          "lat": 21.2,
          "lon": 111.63,
          "date": "2026-05-29",
          "detections": 1
        },
        {
          "lat": 23.22,
          "lon": 118.08,
          "date": "2026-05-26",
          "detections": 1
        },
        {
          "lat": 22.04,
          "lon": 113.1,
          "date": "2026-05-24",
          "detections": 1
        },
        {
          "lat": 30.49,
          "lon": 120.98,
          "date": "2026-06-04",
          "detections": 1
        },
        {
          "lat": 30.54,
          "lon": 122.17,
          "date": "2026-05-23",
          "detections": 1
        },
        {
          "lat": 22.79,
          "lon": 117.64,
          "date": "2026-06-07",
          "detections": 2
        },
        {
          "lat": 22.74,
          "lon": 116.12,
          "date": "2026-05-26",
          "detections": 1
        },
        {
          "lat": 24.08,
          "lon": 119.37,
          "date": "2026-06-02",
          "detections": 1
        },
        {
          "lat": 22.4,
          "lon": 121.58,
          "date": "2026-05-16",
          "detections": 1
        },
        {
          "lat": 22.9,
          "lon": 117.71,
          "date": "2026-06-07",
          "detections": 1
        },
        {
          "lat": 29.59,
          "lon": 123.14,
          "date": "2026-06-04",
          "detections": 1
        },
        {
          "lat": 16.17,
          "lon": 120.39,
          "date": "2026-05-13",
          "detections": 1
        },
        {
          "lat": 28.84,
          "lon": 122.69,
          "date": "2026-05-23",
          "detections": 1
        },
        {
          "lat": 34.77,
          "lon": 127.43,
          "date": "2026-06-01",
          "detections": 1
        },
        {
          "lat": 27.83,
          "lon": 120.97,
          "date": "2026-05-16",
          "detections": 1
        },
        {
          "lat": 29.09,
          "lon": 122.26,
          "date": "2026-06-04",
          "detections": 1
        },
        {
          "lat": 20.35,
          "lon": 110.73,
          "date": "2026-06-03",
          "detections": 1
        },
        {
          "lat": 30.37,
          "lon": 122.23,
          "date": "2026-05-23",
          "detections": 1
        },
        {
          "lat": 29.25,
          "lon": 122.02,
          "date": "2026-06-04",
          "detections": 1
        },
        {
          "lat": 24.54,
          "lon": 118.38,
          "date": "2026-06-02",
          "detections": 1
        },
        {
          "lat": 22.88,
          "lon": 119.66,
          "date": "2026-05-18",
          "detections": 1
        },
        {
          "lat": 23.14,
          "lon": 116.63,
          "date": "2026-06-07",
          "detections": 1
        },
        {
          "lat": 31.77,
          "lon": 121.11,
          "date": "2026-05-23",
          "detections": 1
        },
        {
          "lat": 21.12,
          "lon": 111.37,
          "date": "2026-05-17",
          "detections": 1
        },
        {
          "lat": 28.81,
          "lon": 122.24,
          "date": "2026-05-23",
          "detections": 1
        },
        {
          "lat": 22.72,
          "lon": 116.49,
          "date": "2026-05-26",
          "detections": 1
        },
        {
          "lat": 21.06,
          "lon": 112.44,
          "date": "2026-05-17",
          "detections": 1
        },
        {
          "lat": 25.54,
          "lon": 119.68,
          "date": "2026-05-21",
          "detections": 1
        },
        {
          "lat": 27.47,
          "lon": 120.71,
          "date": "2026-05-16",
          "detections": 1
        },
        {
          "lat": 29.04,
          "lon": 122.61,
          "date": "2026-06-04",
          "detections": 1
        },
        {
          "lat": 27.61,
          "lon": 120.87,
          "date": "2026-05-28",
          "detections": 1
        },
        {
          "lat": 25.58,
          "lon": 119.63,
          "date": "2026-05-21",
          "detections": 1
        },
        {
          "lat": 30.52,
          "lon": 121.09,
          "date": "2026-05-23",
          "detections": 1
        },
        {
          "lat": 34.95,
          "lon": 119.83,
          "date": "2026-05-28",
          "detections": 1
        },
        {
          "lat": 33.95,
          "lon": 126.21,
          "date": "2026-05-20",
          "detections": 1
        },
        {
          "lat": 34.59,
          "lon": 126.15,
          "date": "2026-05-20",
          "detections": 1
        },
        {
          "lat": 24.16,
          "lon": 119.79,
          "date": "2026-05-21",
          "detections": 1
        },
        {
          "lat": 21.58,
          "lon": 112.19,
          "date": "2026-05-17",
          "detections": 1
        },
        {
          "lat": 19.43,
          "lon": 122.34,
          "date": "2026-06-06",
          "detections": 1
        },
        {
          "lat": 26.44,
          "lon": 119.97,
          "date": "2026-05-28",
          "detections": 1
        },
        {
          "lat": 21.75,
          "lon": 113.26,
          "date": "2026-05-24",
          "detections": 1
        },
        {
          "lat": 20.87,
          "lon": 111.68,
          "date": "2026-05-17",
          "detections": 1
        },
        {
          "lat": 31.1,
          "lon": 122.07,
          "date": "2026-05-23",
          "detections": 1
        },
        {
          "lat": 22.73,
          "lon": 117.12,
          "date": "2026-05-14",
          "detections": 1
        },
        {
          "lat": 24.81,
          "lon": 120.21,
          "date": "2026-06-02",
          "detections": 1
        },
        {
          "lat": 27.18,
          "lon": 123.57,
          "date": "2026-06-04",
          "detections": 1
        },
        {
          "lat": 20.25,
          "lon": 110.94,
          "date": "2026-05-17",
          "detections": 1
        },
        {
          "lat": 26.52,
          "lon": 119.82,
          "date": "2026-05-21",
          "detections": 1
        },
        {
          "lat": 31.22,
          "lon": 122.27,
          "date": "2026-05-23",
          "detections": 1
        },
        {
          "lat": 29.7,
          "lon": 122.38,
          "date": "2026-06-04",
          "detections": 1
        },
        {
          "lat": 27.93,
          "lon": 122.72,
          "date": "2026-05-23",
          "detections": 1
        },
        {
          "lat": 26.65,
          "lon": 119.79,
          "date": "2026-05-16",
          "detections": 1
        },
        {
          "lat": 29.07,
          "lon": 122.64,
          "date": "2026-05-23",
          "detections": 1
        },
        {
          "lat": 23.91,
          "lon": 117.98,
          "date": "2026-05-14",
          "detections": 1
        },
        {
          "lat": 23.15,
          "lon": 117.16,
          "date": "2026-05-26",
          "detections": 1
        },
        {
          "lat": 32.34,
          "lon": 122.55,
          "date": "2026-05-23",
          "detections": 1
        },
        {
          "lat": 23.17,
          "lon": 118.37,
          "date": "2026-05-26",
          "detections": 1
        },
        {
          "lat": 29.3,
          "lon": 122.05,
          "date": "2026-05-23",
          "detections": 1
        },
        {
          "lat": 29.07,
          "lon": 121.99,
          "date": "2026-06-04",
          "detections": 1
        },
        {
          "lat": 34.61,
          "lon": 126.21,
          "date": "2026-06-01",
          "detections": 1
        },
        {
          "lat": 25.09,
          "lon": 119.07,
          "date": "2026-05-21",
          "detections": 1
        },
        {
          "lat": 25.38,
          "lon": 121.28,
          "date": "2026-05-18",
          "detections": 1
        },
        {
          "lat": 24.34,
          "lon": 118.16,
          "date": "2026-06-02",
          "detections": 1
        },
        {
          "lat": 18.83,
          "lon": 122.74,
          "date": "2026-05-13",
          "detections": 1
        },
        {
          "lat": 20.89,
          "lon": 112.13,
          "date": "2026-05-17",
          "detections": 1
        },
        {
          "lat": 29.16,
          "lon": 122.76,
          "date": "2026-05-23",
          "detections": 1
        },
        {
          "lat": 19.5,
          "lon": 110.88,
          "date": "2026-05-17",
          "detections": 1
        },
        {
          "lat": 29.69,
          "lon": 123.07,
          "date": "2026-05-23",
          "detections": 1
        },
        {
          "lat": 25.78,
          "lon": 120.14,
          "date": "2026-05-18",
          "detections": 1
        },
        {
          "lat": 22.8,
          "lon": 117.06,
          "date": "2026-05-26",
          "detections": 1
        },
        {
          "lat": 21.02,
          "lon": 111.79,
          "date": "2026-05-17",
          "detections": 1
        },
        {
          "lat": 23.85,
          "lon": 117.96,
          "date": "2026-06-07",
          "detections": 1
        },
        {
          "lat": 25.23,
          "lon": 121.79,
          "date": "2026-05-18",
          "detections": 1
        },
        {
          "lat": 21.55,
          "lon": 112.52,
          "date": "2026-06-05",
          "detections": 1
        },
        {
          "lat": 29.92,
          "lon": 122.05,
          "date": "2026-05-23",
          "detections": 1
        },
        {
          "lat": 23.3,
          "lon": 117.38,
          "date": "2026-06-07",
          "detections": 2
        },
        {
          "lat": 27.09,
          "lon": 120.62,
          "date": "2026-05-28",
          "detections": 1
        },
        {
          "lat": 21.14,
          "lon": 111.63,
          "date": "2026-05-17",
          "detections": 1
        },
        {
          "lat": 21.76,
          "lon": 112.18,
          "date": "2026-05-29",
          "detections": 1
        },
        {
          "lat": 27.87,
          "lon": 122.71,
          "date": "2026-05-23",
          "detections": 1
        },
        {
          "lat": 27.53,
          "lon": 120.79,
          "date": "2026-05-16",
          "detections": 1
        },
        {
          "lat": 21.06,
          "lon": 110.57,
          "date": "2026-05-22",
          "detections": 1
        },
        {
          "lat": 20.21,
          "lon": 110.33,
          "date": "2026-05-22",
          "detections": 1
        },
        {
          "lat": 28.64,
          "lon": 122.97,
          "date": "2026-06-04",
          "detections": 1
        },
        {
          "lat": 27.57,
          "lon": 120.75,
          "date": "2026-05-16",
          "detections": 1
        },
        {
          "lat": 30.39,
          "lon": 122.77,
          "date": "2026-05-23",
          "detections": 1
        },
        {
          "lat": 20.39,
          "lon": 112.0,
          "date": "2026-05-17",
          "detections": 1
        },
        {
          "lat": 25.0,
          "lon": 119.87,
          "date": "2026-06-02",
          "detections": 1
        },
        {
          "lat": 30.63,
          "lon": 121.8,
          "date": "2026-05-23",
          "detections": 1
        },
        {
          "lat": 20.97,
          "lon": 111.96,
          "date": "2026-05-17",
          "detections": 1
        },
        {
          "lat": 23.46,
          "lon": 117.6,
          "date": "2026-05-26",
          "detections": 1
        },
        {
          "lat": 22.02,
          "lon": 113.26,
          "date": "2026-05-24",
          "detections": 1
        },
        {
          "lat": 20.08,
          "lon": 112.68,
          "date": "2026-05-29",
          "detections": 1
        },
        {
          "lat": 27.07,
          "lon": 121.71,
          "date": "2026-05-28",
          "detections": 1
        },
        {
          "lat": 23.84,
          "lon": 118.07,
          "date": "2026-06-02",
          "detections": 1
        },
        {
          "lat": 20.9,
          "lon": 110.49,
          "date": "2026-05-17",
          "detections": 1
        },
        {
          "lat": 22.06,
          "lon": 114.19,
          "date": "2026-05-24",
          "detections": 1
        },
        {
          "lat": 20.71,
          "lon": 110.66,
          "date": "2026-05-17",
          "detections": 1
        },
        {
          "lat": 24.76,
          "lon": 120.04,
          "date": "2026-06-02",
          "detections": 1
        },
        {
          "lat": 34.86,
          "lon": 126.21,
          "date": "2026-05-20",
          "detections": 1
        },
        {
          "lat": 31.09,
          "lon": 122.6,
          "date": "2026-06-04",
          "detections": 1
        },
        {
          "lat": 24.93,
          "lon": 119.9,
          "date": "2026-05-21",
          "detections": 1
        },
        {
          "lat": 29.56,
          "lon": 122.68,
          "date": "2026-06-04",
          "detections": 1
        },
        {
          "lat": 20.16,
          "lon": 110.14,
          "date": "2026-05-22",
          "detections": 1
        },
        {
          "lat": 20.9,
          "lon": 111.56,
          "date": "2026-05-17",
          "detections": 1
        },
        {
          "lat": 30.2,
          "lon": 122.26,
          "date": "2026-05-23",
          "detections": 1
        },
        {
          "lat": 30.69,
          "lon": 122.4,
          "date": "2026-06-04",
          "detections": 1
        },
        {
          "lat": 21.0,
          "lon": 112.0,
          "date": "2026-05-29",
          "detections": 1
        },
        {
          "lat": 20.85,
          "lon": 113.29,
          "date": "2026-06-05",
          "detections": 1
        },
        {
          "lat": 21.0,
          "lon": 112.0,
          "date": "2026-05-17",
          "detections": 1
        },
        {
          "lat": 22.55,
          "lon": 116.57,
          "date": "2026-05-14",
          "detections": 1
        },
        {
          "lat": 25.7,
          "lon": 120.1,
          "date": "2026-05-18",
          "detections": 1
        },
        {
          "lat": 30.22,
          "lon": 121.84,
          "date": "2026-05-23",
          "detections": 1
        },
        {
          "lat": 24.88,
          "lon": 119.06,
          "date": "2026-06-02",
          "detections": 1
        },
        {
          "lat": 24.88,
          "lon": 120.57,
          "date": "2026-05-18",
          "detections": 1
        },
        {
          "lat": 24.71,
          "lon": 120.03,
          "date": "2026-05-21",
          "detections": 1
        },
        {
          "lat": 20.06,
          "lon": 120.27,
          "date": "2026-05-18",
          "detections": 1
        },
        {
          "lat": 31.35,
          "lon": 122.81,
          "date": "2026-05-23",
          "detections": 1
        },
        {
          "lat": 29.63,
          "lon": 122.47,
          "date": "2026-05-23",
          "detections": 1
        },
        {
          "lat": 34.42,
          "lon": 126.42,
          "date": "2026-05-20",
          "detections": 1
        },
        {
          "lat": 24.13,
          "lon": 119.87,
          "date": "2026-06-02",
          "detections": 1
        },
        {
          "lat": 22.07,
          "lon": 113.98,
          "date": "2026-06-05",
          "detections": 1
        },
        {
          "lat": 20.92,
          "lon": 112.08,
          "date": "2026-05-17",
          "detections": 1
        },
        {
          "lat": 20.7,
          "lon": 111.67,
          "date": "2026-05-29",
          "detections": 1
        },
        {
          "lat": 25.04,
          "lon": 121.03,
          "date": "2026-05-16",
          "detections": 1
        },
        {
          "lat": 29.66,
          "lon": 122.78,
          "date": "2026-05-23",
          "detections": 1
        },
        {
          "lat": 21.47,
          "lon": 111.69,
          "date": "2026-05-17",
          "detections": 1
        },
        {
          "lat": 23.24,
          "lon": 122.27,
          "date": "2026-05-16",
          "detections": 1
        },
        {
          "lat": 23.76,
          "lon": 118.01,
          "date": "2026-06-07",
          "detections": 1
        },
        {
          "lat": 26.44,
          "lon": 120.34,
          "date": "2026-05-16",
          "detections": 1
        },
        {
          "lat": 19.47,
          "lon": 119.61,
          "date": "2026-05-18",
          "detections": 1
        },
        {
          "lat": 27.22,
          "lon": 120.72,
          "date": "2026-05-28",
          "detections": 1
        },
        {
          "lat": 25.51,
          "lon": 122.08,
          "date": "2026-05-18",
          "detections": 1
        },
        {
          "lat": 21.76,
          "lon": 113.22,
          "date": "2026-05-24",
          "detections": 1
        },
        {
          "lat": 24.72,
          "lon": 119.91,
          "date": "2026-05-18",
          "detections": 1
        },
        {
          "lat": 22.84,
          "lon": 116.71,
          "date": "2026-06-07",
          "detections": 1
        },
        {
          "lat": 25.92,
          "lon": 120.54,
          "date": "2026-05-16",
          "detections": 1
        },
        {
          "lat": 20.97,
          "lon": 111.73,
          "date": "2026-05-29",
          "detections": 1
        },
        {
          "lat": 31.86,
          "lon": 121.89,
          "date": "2026-05-23",
          "detections": 1
        },
        {
          "lat": 20.92,
          "lon": 112.08,
          "date": "2026-05-29",
          "detections": 1
        },
        {
          "lat": 27.68,
          "lon": 123.64,
          "date": "2026-05-23",
          "detections": 1
        },
        {
          "lat": 29.92,
          "lon": 122.57,
          "date": "2026-06-04",
          "detections": 1
        },
        {
          "lat": 18.98,
          "lon": 110.7,
          "date": "2026-05-22",
          "detections": 1
        },
        {
          "lat": 23.6,
          "lon": 117.18,
          "date": "2026-06-07",
          "detections": 1
        },
        {
          "lat": 20.91,
          "lon": 110.45,
          "date": "2026-05-17",
          "detections": 1
        },
        {
          "lat": 30.8,
          "lon": 123.09,
          "date": "2026-05-23",
          "detections": 1
        },
        {
          "lat": 25.59,
          "lon": 119.85,
          "date": "2026-05-16",
          "detections": 1
        },
        {
          "lat": 21.71,
          "lon": 112.35,
          "date": "2026-05-29",
          "detections": 1
        },
        {
          "lat": 28.38,
          "lon": 121.66,
          "date": "2026-05-23",
          "detections": 2
        },
        {
          "lat": 32.31,
          "lon": 122.56,
          "date": "2026-05-23",
          "detections": 1
        },
        {
          "lat": 26.99,
          "lon": 122.89,
          "date": "2026-05-23",
          "detections": 1
        },
        {
          "lat": 20.84,
          "lon": 110.57,
          "date": "2026-05-17",
          "detections": 1
        },
        {
          "lat": 25.65,
          "lon": 121.42,
          "date": "2026-05-18",
          "detections": 2
        },
        {
          "lat": 18.59,
          "lon": 110.75,
          "date": "2026-06-03",
          "detections": 1
        },
        {
          "lat": 24.13,
          "lon": 119.91,
          "date": "2026-06-02",
          "detections": 1
        },
        {
          "lat": 20.79,
          "lon": 111.47,
          "date": "2026-05-29",
          "detections": 1
        },
        {
          "lat": 22.83,
          "lon": 116.54,
          "date": "2026-05-26",
          "detections": 1
        },
        {
          "lat": 21.21,
          "lon": 121.35,
          "date": "2026-05-18",
          "detections": 1
        },
        {
          "lat": 20.79,
          "lon": 111.47,
          "date": "2026-05-17",
          "detections": 1
        },
        {
          "lat": 26.54,
          "lon": 120.03,
          "date": "2026-05-28",
          "detections": 1
        },
        {
          "lat": 22.89,
          "lon": 117.42,
          "date": "2026-05-14",
          "detections": 1
        },
        {
          "lat": 29.82,
          "lon": 122.77,
          "date": "2026-06-04",
          "detections": 1
        },
        {
          "lat": 26.75,
          "lon": 119.94,
          "date": "2026-05-28",
          "detections": 1
        },
        {
          "lat": 22.59,
          "lon": 116.93,
          "date": "2026-05-26",
          "detections": 1
        },
        {
          "lat": 21.55,
          "lon": 113.99,
          "date": "2026-06-05",
          "detections": 1
        },
        {
          "lat": 20.58,
          "lon": 112.38,
          "date": "2026-05-17",
          "detections": 1
        },
        {
          "lat": 21.43,
          "lon": 111.95,
          "date": "2026-05-17",
          "detections": 1
        },
        {
          "lat": 25.29,
          "lon": 119.49,
          "date": "2026-06-02",
          "detections": 1
        },
        {
          "lat": 23.43,
          "lon": 120.08,
          "date": "2026-05-18",
          "detections": 1
        }
      ],
      "sub_zones": {
        "north": {
          "name": "東海 / 北方",
          "total_detections": 2471,
          "dark_vessels": 455,
          "dark_ratio": 18.4
        },
        "east": {
          "name": "台灣東部",
          "total_detections": 187,
          "dark_vessels": 90,
          "dark_ratio": 48.1
        },
        "south": {
          "name": "南海北部",
          "total_detections": 2872,
          "dark_vessels": 1112,
          "dark_ratio": 38.7
        },
        "west": {
          "name": "台灣海峽",
          "total_detections": 2007,
          "dark_vessels": 718,
          "dark_ratio": 35.8
        }
      }
    }
  }
}